saz/__init__.py
saz/sazPandas.py
saz/sazPure.py
saz/sazSpark.py
saz-0.1.3.dist-info/licenses/LICENSE
saz-0.1.3.dist-info/METADATA
saz-0.1.3.dist-info/WHEEL
saz-0.1.3.dist-info/top_level.txt
saz-0.1.3.dist-info/RECORD
