Metadata-Version: 2.4
Name: saz
Version: 0.1.3
Summary: Tools for CSV cleaning and reporting
Home-page: https://github.com/samansiadati/saz
Author: Saman Siadati
Author-email: siadatisaman@gmail.com
License: MIT
Project-URL: Bug Tracker, https://github.com/samansiadati/saz/issues
Keywords: pandas,csv,data cleaning,reporting,saz
Classifier: Development Status :: 3 - Alpha
Classifier: Intended Audience :: Developers
Classifier: License :: OSI Approved :: MIT License
Classifier: Programming Language :: Python :: 3.8
Classifier: Programming Language :: Python :: 3.9
Classifier: Programming Language :: Python :: 3.10
License-File: LICENSE
Requires-Dist: pandas
Dynamic: author
Dynamic: author-email
Dynamic: classifier
Dynamic: description
Dynamic: description-content-type
Dynamic: home-page
Dynamic: keywords
Dynamic: license
Dynamic: license-file
Dynamic: project-url
Dynamic: requires-dist
Dynamic: summary
